LICENSE
MANIFEST.in
README.rst
setup.py
subsample/__init__.py
subsample/algorithms.py
subsample/file_input.py
subsample/main.py
subsample.egg-info/PKG-INFO
subsample.egg-info/SOURCES.txt
subsample.egg-info/dependency_links.txt
subsample.egg-info/entry_points.txt
subsample.egg-info/top_level.txt