Metadata-Version: 1.0
Name: subsample
Version: 0.0.4
Summary: Command-line interface for sampling lines from text files
Home-page: https://github.com/paulgb/subsample
Author: Paul Butler
Author-email: paulgb@gmail.com
License: UNKNOWN
Platform: UNKNOWN
